xges/.idea/.gitignore
xges/.idea/inspectionProfiles/Project_Default.xml
xges/.idea/inspectionProfiles/profiles_settings.xml
xges/.idea/misc.xml
xges/.idea/modules.xml
xges/.idea/vcs.xml
xges/.idea/xges.iml
xges/__init__.py
xges/bic_scorer.py
xges/bic_scorer_fast.py
xges/demo_tree.py
xges/edge_queue_set.py
xges/experimental/__init__.py
xges/experimental/neural_nets.py
xges/experimental/trees.py
xges/operators.py
xges/pdag.py
xges/scorer.py
xges/search.py
xges/tes_nn.py
xges/tes_nn2.py
xges-0.1.6.dist-info/METADATA
xges-0.1.6.dist-info/WHEEL
xges-0.1.6.dist-info/RECORD
