Metadata-Version: 2.1
Name: xges
Version: 0.1.6
Summary: 
Author: Achille Nazaret
Author-email: aon2108@columbia.edu
Requires-Python: >=3.9,<4.0
Classifier: Programming Language :: Python :: 3
Classifier: Programming Language :: Python :: 3.9
Classifier: Programming Language :: Python :: 3.10
Classifier: Programming Language :: Python :: 3.11
Classifier: Programming Language :: Python :: 3.12
Requires-Dist: numba (>=0.59.1,<0.60.0)
Requires-Dist: numpy (>=1.26.4,<2.0.0)
Requires-Dist: sortedcontainers (>=2.4.0,<3.0.0)
